dhx_utils/__init__.py
dhx_utils/api.py
dhx_utils/errors.py
dhx_utils/formatter.py
dhx_utils/logger.py
dhx_utils/oms_service.py
dhx_utils/ops_service.py
dhx_utils/resolver.py
dhx_utils/validator.py
dhx_utils/catalog/__init__.py
dhx_utils/catalog/catalog_service.py
dhx_utils/catalog/utils.py
tests/__init__.py
tests/test_api.py
tests/test_errors.py
tests/test_formatter.py
tests/test_oms_service.py
tests/test_resolver.py
tests/test_validator.py
dhx_utils_lib-1.7.9b306+40f53d4c.dist-info/METADATA
dhx_utils_lib-1.7.9b306+40f53d4c.dist-info/WHEEL
dhx_utils_lib-1.7.9b306+40f53d4c.dist-info/top_level.txt
dhx_utils_lib-1.7.9b306+40f53d4c.dist-info/RECORD
