Metadata-Version: 2.1
Name: dhx-utils-lib
Version: 1.7.9b306
Summary: DataHex Utility Library to help with building AWS SAM based application.
Home-page: https://github.com/rozettatechnology/datahex-utils
Author: RoZetta Technology
Author-email: developers@rozettatechnology.com
Classifier: Development Status :: 3 - Alpha
Classifier: Environment :: Console
Classifier: Intended Audience :: Developers
Classifier: License :: Other/Proprietary License
Classifier: Natural Language :: English
Classifier: Operating System :: Unix
Classifier: Programming Language :: Python
Classifier: Topic :: Software Development
Requires-Dist: dnspython (>=2.1.0)
Requires-Dist: retrying (<2.0,>=1.3.3)
Requires-Dist: simplejson (>=3.17.2)
Requires-Dist: requests (<3.0,>=2.4.2)
Requires-Dist: requests-toolbelt (~=0.9.1)
Requires-Dist: sortedcontainers (<3.0.0,>=2.4.0)
